_numpy_rms.abi3.so
numpy_rms/__init__.py
numpy_rms/_rms.c
numpy_rms/_rms_cffi.py
numpy_rms/_version.py
numpy_rms/fallback.py
numpy_rms-0.6.0.dist-info/METADATA
numpy_rms-0.6.0.dist-info/WHEEL
numpy_rms-0.6.0.dist-info/top_level.txt
numpy_rms-0.6.0.dist-info/RECORD
numpy_rms-0.6.0.dist-info/licenses/LICENSE
