Metadata-Version: 2.4
Name: numpy-rms
Version: 0.6.0
Summary: A fast python library for calculating the RMS of a NumPy array
Author: Iver Jordal
License: MIT License
Project-URL: Homepage, https://github.com/nomonosound/numpy-rms
Classifier: Development Status :: 3 - Alpha
Classifier: Intended Audience :: Developers
Classifier: Intended Audience :: Science/Research
Classifier: Topic :: Software Development :: Libraries
Classifier: Topic :: Multimedia :: Sound/Audio
Classifier: Topic :: Scientific/Engineering
Classifier: License :: OSI Approved :: MIT License
Classifier: Programming Language :: Python :: 3.9
Classifier: Programming Language :: Python :: 3.10
Classifier: Programming Language :: Python :: 3.11
Classifier: Programming Language :: Python :: 3.12
Classifier: Programming Language :: Python :: 3.13
License-File: LICENSE
Requires-Dist: cffi>=1.0.0
Requires-Dist: numpy<3,>=2
Dynamic: license-file
